test/__init__.py
test/__main__.py
tw_stock_plugin/__init__.py
tw_stock_plugin/config.py
tw_stock_plugin/constant.py
tw_stock_plugin/regex_pattern.py
tw_stock_plugin/core/__init__.py
tw_stock_plugin/core/stock_info.py
tw_stock_plugin/core/stock_institutional_investors.py
tw_stock_plugin/core/stock_margin_trading.py
tw_stock_plugin/core/stock_peratio.py
tw_stock_plugin/core/stock_shareholdings.py
tw_stock_plugin/core/stock_tools.py
tw_stock_plugin/core/stock_trading.py
tw_stock_plugin/core/update_stock.py
tw_stock_plugin/object/__init__.py
tw_stock_plugin/object/stock_info.py
tw_stock_plugin/object/stock_institutional_investors.py
tw_stock_plugin/object/stock_margin_trading.py
tw_stock_plugin/object/stock_peratio.py
tw_stock_plugin/object/stock_shareholdings.py
tw_stock_plugin/object/stock_trading.py
tw_stock_plugin/utils/__init__.py
tw_stock_plugin/utils/response_handler.py
tw_stock_plugin/utils/schema.py
tw_stock_plugin-0.1.5.dist-info/METADATA
tw_stock_plugin-0.1.5.dist-info/WHEEL
tw_stock_plugin-0.1.5.dist-info/entry_points.txt
tw_stock_plugin-0.1.5.dist-info/top_level.txt
tw_stock_plugin-0.1.5.dist-info/RECORD
