Metadata-Version: 2.1
Name: tw-stock-plugin
Version: 0.1.5
Summary: Some util function when doing Taiwan stock web scraping and some common stock data parser
Home-page: https://github.com/chienfeng0719/tw-stock-plugin
Author: Jimmy Yeh
Author-email: chienfeng0719@hotmail.com
License: UNKNOWN
Platform: UNKNOWN
Classifier: Programming Language :: Python :: 3
Classifier: License :: OSI Approved :: MIT License
Classifier: Operating System :: OS Independent
Requires-Python: >=3.6
Requires-Dist: pandas (==1.1.0)
Requires-Dist: numpy (==1.19.1)
Requires-Dist: requests (==2.24.0)
Requires-Dist: lxml (==4.6.3)
Requires-Dist: schema (==0.7.2)
